Open_Excel_Processor/__init__.py
Open_Excel_Processor/main.py
Open_Excel_Processor-0.3.5.dist-info/LICENSE.txt
Open_Excel_Processor-0.3.5.dist-info/METADATA
Open_Excel_Processor-0.3.5.dist-info/WHEEL
Open_Excel_Processor-0.3.5.dist-info/top_level.txt
Open_Excel_Processor-0.3.5.dist-info/RECORD
