Metadata-Version: 2.1
Name: Open-Excel-Processor
Version: 0.3.5
Summary: A library to interact with Excel files and process data
Author: Cobra Author
Author-email: cobraauthor@gmail.com
License-File: LICENSE.txt
Requires-Dist: pymongo
Requires-Dist: datetime
